falcon_jinja2/__init__.py
falcon_jinja2/template.py
falcon_jinja2-0.0.2.dist-info/LICENSE
falcon_jinja2-0.0.2.dist-info/METADATA
falcon_jinja2-0.0.2.dist-info/WHEEL
falcon_jinja2-0.0.2.dist-info/top_level.txt
falcon_jinja2-0.0.2.dist-info/RECORD
